geomap/__init__.py
geomap/geomap.py
geomap-0.2.1.data/scripts/geo-map
geomap-0.2.1.dist-info/DESCRIPTION.rst
geomap-0.2.1.dist-info/METADATA
geomap-0.2.1.dist-info/metadata.json
geomap-0.2.1.dist-info/RECORD
geomap-0.2.1.dist-info/top_level.txt
geomap-0.2.1.dist-info/WHEEL
