Metadata-Version: 2.0
Name: geomap
Version: 0.2.1
Summary: Generate a map of geolocations
Home-page: https://github.com/amiralis/geo-mapper
Author: Amirali Sanatinia
Author-email: amirali@ccs.neu.edu
License: Apache 2
Platform: UNKNOWN
Classifier: License :: OSI Approved :: Apache Software License
Classifier: Programming Language :: Python :: 2.7
Classifier: Programming Language :: Python :: 3.2
Classifier: Programming Language :: Python :: 3.3
Classifier: Programming Language :: Python :: 3.4
Classifier: Topic :: Scientific/Engineering :: Visualization
Requires-Dist: basemap
Requires-Dist: matplotlib
